XStatic_Bootstrap-4.5.3.1-py3.13-nspkg.pth
xstatic/pkg/bootstrap/__init__.py
xstatic/pkg/bootstrap/data/css/bootstrap-grid.css
xstatic/pkg/bootstrap/data/css/bootstrap-grid.css.map
xstatic/pkg/bootstrap/data/css/bootstrap-grid.min.css
xstatic/pkg/bootstrap/data/css/bootstrap-grid.min.css.map
xstatic/pkg/bootstrap/data/css/bootstrap-reboot.css
xstatic/pkg/bootstrap/data/css/bootstrap-reboot.css.map
xstatic/pkg/bootstrap/data/css/bootstrap-reboot.min.css
xstatic/pkg/bootstrap/data/css/bootstrap-reboot.min.css.map
xstatic/pkg/bootstrap/data/css/bootstrap.css
xstatic/pkg/bootstrap/data/css/bootstrap.css.map
xstatic/pkg/bootstrap/data/css/bootstrap.min.css
xstatic/pkg/bootstrap/data/css/bootstrap.min.css.map
xstatic/pkg/bootstrap/data/js/bootstrap.bundle.js
xstatic/pkg/bootstrap/data/js/bootstrap.bundle.js.map
xstatic/pkg/bootstrap/data/js/bootstrap.bundle.min.js
xstatic/pkg/bootstrap/data/js/bootstrap.bundle.min.js.map
xstatic/pkg/bootstrap/data/js/bootstrap.js
xstatic/pkg/bootstrap/data/js/bootstrap.js.map
xstatic/pkg/bootstrap/data/js/bootstrap.min.js
xstatic/pkg/bootstrap/data/js/bootstrap.min.js.map
xstatic_bootstrap-4.5.3.1.dist-info/METADATA
xstatic_bootstrap-4.5.3.1.dist-info/WHEEL
xstatic_bootstrap-4.5.3.1.dist-info/namespace_packages.txt
xstatic_bootstrap-4.5.3.1.dist-info/top_level.txt
xstatic_bootstrap-4.5.3.1.dist-info/RECORD
