Metadata-Version: 2.4
Name: XStatic-Bootstrap
Version: 4.5.3.1
Summary: Bootstrap 4.5.3 (XStatic packaging standard)
Home-page: https://getbootstrap.com/
Maintainer: Thomas Waldmann
Maintainer-email: tw@waldmann-edv.de
License: (same as Bootstrap)
Keywords: bootstrap xstatic
Platform: any
Dynamic: description
Dynamic: home-page
Dynamic: keywords
Dynamic: license
Dynamic: maintainer
Dynamic: maintainer-email
Dynamic: platform
Dynamic: summary
